rebels/__init__.py
rebels/solution.py
rebels-0.0.2.dist-info/LICENSE
rebels-0.0.2.dist-info/METADATA
rebels-0.0.2.dist-info/WHEEL
rebels-0.0.2.dist-info/top_level.txt
rebels-0.0.2.dist-info/RECORD
